Interrupt Controller/design.sv
module interrupt_controller(
  //Processor
  pclk_i,prst_i,paddr_i,pwdata_i,prdata_o,pwrite_i,penable_i,pready_o,pslverr_o,
  intr_to_service_o,intr_valid_o,intr_serviced_i,
  //Peripheral Controllers
  intr_active_i
);
  
  //penable_i is given by processor
  //pready_o is given by Interrupt Controller
  
  parameter NUM_INTR 		= 16;
  parameter S_NO_INTR 		= 3'b000;
  parameter S_INTR_ACTIVE 	= 3'b001;
  parameter S_INTR_GIVEN_TO_PROC = 3'b010;
  parameter S_INTR_SERVICED = 3'b011;
  parameter S_INTR_ERROR 		= 3'b100;
  
  input pclk_i,prst_i,pwrite_i,penable_i;
  input [7:0] paddr_i;
  input [7:0] pwdata_i;
  output reg [7:0] prdata_o;
  output reg pready_o;
  output reg pslverr_o;
  output reg [3:0] intr_to_service_o;
  output reg intr_valid_o;
  input intr_serviced_i;
  input [NUM_INTR-1:0] intr_active_i;
  
  integer i;
  reg first_match_f;
  reg [3:0] highest_priority;
  reg [3:0] intr_with_highest_prio;
  
  //Array to registers to decide the prioroty of the interrupts by the processor
  reg [7:0] priority_regA[NUM_INTR-1:0]; //16 registers
  
  //For State Machine to be implemented
  reg [2:0] state, next_state;
  
  always @(next_state) begin
    state = next_state;
  end
  
  //Process 1 - Programming (writing the priority and reading) the registers
  always @(posedge pclk_i) begin
    
    if(prst_i == 1) begin
      //Reset all the reg variables
      prdata_o = 0;
      pready_o = 0;
      pslverr_o = 0;
      intr_to_service_o = 0;
      intr_valid_o = 0;
      first_match_f = 0;
      highest_priority = 0;
      intr_with_highest_prio = 0;
      for (i=0 ; i<NUM_INTR ; i=i+1) begin
        priority_regA[i] = 0;
      end
      state = S_NO_INTR;
      next_state = S_NO_INTR;
    end
    
    else begin
      if (penable_i == 1) begin
        pready_o = 1;
        if(pwrite_i == 1) begin
          priority_regA[paddr_i] = pwdata_i;
        end
        else begin
          prdata_o = priority_regA[paddr_i];
        end
      end
    end
  end
  
  //Process 2 - Interrupt Handling: Actual functionality of Interrupt Controller
  //Interrupt Handling is implemented by STATE MACHINES
  always @(posedge pclk_i) begin
    case(state)
      
      S_NO_INTR: begin
        if(intr_active_i != 0) begin
          next_state = S_INTR_ACTIVE;
          first_match_f = 1;
        end
      end
      
      S_INTR_ACTIVE: begin
        //Figure out the highest priority interrupt amongst all the active interrupts
        for (i=0 ; i<NUM_INTR ; i=i+1) begin
          if (intr_active_i != 0) begin
            if (first_match_f == 1) begin
              highest_priority = priority_regA[i];
              intr_with_highest_prio = i;
              first_match_f = 0; //One time only to get the reference value
            end
            else begin
              if (highest_priority < priority_regA[i]) begin
                highest_priority = priority_regA[i];
                intr_with_highest_prio = i;
              end
            end
          end
        end
        next_state = S_INTR_GIVEN_TO_PROC;
      end
      
      S_INTR_GIVEN_TO_PROC: begin
        intr_to_service_o = intr_with_highest_prio;
        intr_valid_o = 1;
        first_match_f = 1;
        next_state = S_INTR_SERVICED;
      end
      
      S_INTR_SERVICED: begin
        if (intr_serviced_i == 1) begin
          intr_to_service_o = 0;
          intr_valid_o = 0;
          if (intr_active_i != 0) begin
            next_state = S_INTR_ACTIVE;
          end
          else begin
            next_state = S_NO_INTR;
          end
        end
        else begin
          next_state = S_INTR_SERVICED;
        end
      end
      
      S_INTR_ERROR: begin
        //Will be implemented later
      end
      
    endcase
  end
  
  
endmodule

Interrupt Controller/testbench.sv
module tb_INTC;
  
  parameter NUM_INTR = 16;
  
  reg pclk_i,prst_i,pwrite_i,penable_i;
  reg [7:0] paddr_i;
  reg [7:0] pwdata_i;
  wire [7:0] prdata_o;
  wire pready_o;
  wire pslverr_o;
  wire [3:0] intr_to_service_o;
  wire intr_valid_o;
  reg intr_serviced_i;
  reg [NUM_INTR-1:0] intr_active_i;
  
  integer i;
  
  interrupt_controller dut (
    //Processor
    pclk_i,prst_i,paddr_i,pwdata_i,prdata_o,pwrite_i,penable_i,pready_o,pslverr_o,
    intr_to_service_o,intr_valid_o,intr_serviced_i,
    //Peripheral Controllers
    intr_active_i
	);
  
  initial begin
    pclk_i = 0;
    forever #5 pclk_i = ~pclk_i;
  end
  
  initial begin
    prst_i = 1;
    intr_active_i = 0;
    paddr_i = 0;
    pwrite_i = 0;
    pwdata_i = 0;
    penable_i = 0;
    repeat(2) @(posedge pclk_i);
    prst_i = 0;
    
    //Apply stimulus
    //Step1: Program the priority registers
    /*for(i=0 ; i<NUM_INTR ; i=i+1) begin
      //reg_write(i,i); //LOWEST Priority
      reg_write(i,NUM_INTR-1-i); //HIGHEST Priority
    end*/
    //For random priority generation
    reg_write(0,10);
    reg_write(1,15);
    reg_write(2,7);
    reg_write(3,5);
    reg_write(4,6);
    reg_write(5,3);
    reg_write(6,8);
    reg_write(7,4);
    reg_write(8,0);
    reg_write(9,1);
    reg_write(10,11);
    reg_write(11,2);
    reg_write(12,13);
    reg_write(13,9);
    reg_write(14,14);
    reg_write(15,12);
    
    //To generate interrupts
    intr_active_i = $random;
    #100;
    intr_active_i = intr_active_i | $random;
    #1000;
    intr_active_i = intr_active_i | $random;
    #2000;
    $finish;
    
  end
  
  //Service the interrupt
  initial begin
    forever begin
      @(posedge pclk_i);
      if(intr_valid_o == 1) begin
        //Take some time to service the interrupt
        #20;
        //Drop the interrupt once it is being serviced
        intr_active_i[intr_to_service_o] = 0; //Dropping the interrupt
        intr_serviced_i = 1;
        #10;
        intr_serviced_i = 0;
      end
    end
  end
  
  task reg_write(input [7:0] addr, input [7:0] data);
    begin
      @(posedge pclk_i);
      paddr_i = addr;
      pwdata_i = data; //(i: giving Lowest Priority and 15-i: giving Highest Priority) (Can't use $random -> same priority might be assigned)
      pwrite_i = 1;
      penable_i = 1;
      wait (pready_o == 1);
      @(posedge pclk_i);
      pwrite_i = 0;
      penable_i = 0;
      paddr_i = 0;
      pwdata_i = 0;
    end
  endtask
  
  initial begin
    $dumpfile("intc.vcd");
    $dumpvars(0,tb_INTC);
  end
endmodule

Interrupt Controller/Interrupt Controller.sim/sim_1/behav/xsim/intc.vcd
$date
   Sun Jan 24 12:50:53 2021
$end
$version
  2020.1
$end
$timescale
  1ps
$end
$scope module tb_INTC $end
$var reg 1 ! pclk_i $end
$var reg 1 " prst_i $end
$var reg 1 # pwrite_i $end
$var reg 1 $ penable_i $end
$var reg 8 % paddr_i [7:0] $end
$var reg 8 & pwdata_i [7:0] $end
$var wire 8 ' prdata_o [7:0] $end
$var wire 1 ( pready_o $end
$var wire 1 ) pslverr_o $end
$var wire 4 * intr_to_service_o [3:0] $end
$var wire 1 + intr_valid_o $end
$var reg 1 , intr_serviced_i $end
$var reg 16 - intr_active_i [15:0] $end
$var integer 32 . i $end
$var parameter 32 / NUM_INTR [31:0] $end
$scope module dut $end
$var wire 1 0 pclk_i $end
$var wire 1 1 prst_i $end
$var wire 1 2 pwrite_i $end
$var wire 1 3 penable_i $end
$var wire 8 4 paddr_i [7:0] $end
$var wire 8 5 pwdata_i [7:0] $end
$var reg 8 6 prdata_o [7:0] $end
$var reg 1 7 pready_o $end
$var reg 1 8 pslverr_o $end
$var reg 4 9 intr_to_service_o [3:0] $end
$var reg 1 : intr_valid_o $end
$var wire 1 ; intr_serviced_i $end
$var wire 16 < intr_active_i [15:0] $end
$var integer 32 = i $end
$var reg 1 > first_match_f $end
$var reg 4 ? highest_priority [3:0] $end
$var reg 4 @ intr_with_highest_prio [3:0] $end
$var reg 3 A state [2:0] $end
$var reg 3 B next_state [2:0] $end
$var parameter 32 C NUM_INTR [31:0] $end
$var parameter 3 D S_NO_INTR [2:0] $end
$var parameter 3 E S_INTR_ACTIVE [2:0] $end
$var parameter 3 F S_INTR_GIVEN_TO_PROC [2:0] $end
$var parameter 3 G S_INTR_SERVICED [2:0] $end
$var parameter 3 H S_INTR_ERROR [2:0] $end
$upscope $end
$scope task reg_write $end
$var reg 8 I addr [7:0] $end
$var reg 8 J data [7:0] $end
$upscope $end
$upscope $end
$enddefinitions $end
#0
$dumpvars
0!
1"
x#
x$
bx %
bx &
bx '
x(
x)
bx *
x+
x,
bx -
bx .
b10000 /
00
11
x2
x3
bx 4
bx 5
bx 6
x7
x8
bx 9
x:
x;
bx <
bx =
x>
bx ?
bx @
bx A
bx B
b10000 C
b0 D
b1 E
b10 F
b11 G
b100 H
bx I
bx J
$end
#5000
1!
b0 '
0(
0)
b0 *
0+
10
b0 6
07
08
b0 9
0:
b10000 =
0>
b0 ?
b0 @
b0 A
b0 B
#10000
0!
00
#15000
1!
0"
10
01
b0 I
b1010 J
#20000
0!
00
#25000
1!
1#
1$
b0 %
b1010 &
1(
10
12
13
b0 4
b1010 5
17
#30000
0!
00
#35000
1!
0#
0$
b0 %
b0 &
10
02
03
b0 5
b1 I
b1111 J
#40000
0!
00
#45000
1!
1#
1$
b1 %
b1111 &
10
12
13
b1 4
b1111 5
17
#50000
0!
00
#55000
1!
0#
0$
b0 %
b0 &
10
02
03
b0 4
b0 5
b10 I
b111 J
#60000
0!
00
#65000
1!
1#
1$
b10 %
b111 &
10
12
13
b10 4
b111 5
17
#70000
0!
00
#75000
1!
0#
0$
b0 %
b0 &
10
02
03
b0 4
b0 5
b11 I
b101 J
#80000
0!
00
#85000
1!
1#
1$
b11 %
b101 &
10
12
13
b11 4
b101 5
17
#90000
0!
00
#95000
1!
0#
0$
b0 %
b0 &
10
02
03
b0 4
b0 5
b100 I
b110 J
#100000
0!
00
#105000
1!
1#
1$
b100 %
b110 &
10
12
13
b100 4
b110 5
17
#110000
0!
00
#115000
1!
0#
0$
b0 %
b0 &
10
02
03
b0 4
b0 5
b101 I
b11 J
#120000
0!
00
#125000
1!
1#
1$
b101 %
b11 &
10
12
13
b101 4
b11 5
17
#130000
0!
00
#135000
1!
0#
0$
b0 %
b0 &
10
02
03
b0 4
b0 5
b110 I
b1000 J
#140000
0!
00
#145000
1!
1#
1$
b110 %
b1000 &
10
12
13
b110 4
b1000 5
17
#150000
0!
00
#155000
1!
0#
0$
b0 %
b0 &
10
02
03
b0 4
b0 5
b111 I
b100 J
#160000
0!
00
#165000
1!
1#
1$
b111 %
b100 &
10
12
13
b111 4
b100 5
17
#170000
0!
00
#175000
1!
0#
0$
b0 %
b0 &
10
02
03
b0 4
b0 5
b1000 I
b0 J
#180000
0!
00
#185000
1!
1#
1$
b1000 %
b0 &
10
12
13
b1000 4
17
#190000
0!
00
#195000
1!
0#
0$
b0 %
b0 &
10
02
03
b0 4
b1001 I
b1 J
#200000
0!
00
#205000
1!
1#
1$
b1001 %
b1 &
10
12
13
b1001 4
b1 5
17
#210000
0!
00
#215000
1!
0#
0$
b0 %
b0 &
10
02
03
b0 4
b0 5
b1010 I
b1011 J
#220000
0!
00
#225000
1!
1#
1$
b1010 %
b1011 &
10
12
13
b1010 4
b1011 5
17
#230000
0!
00
#235000
1!
0#
0$
b0 %
b0 &
10
02
03
b0 4
b0 5
b1011 I
b10 J
#240000
0!
00
#245000
1!
1#
1$
b1011 %
b10 &
10
12
13
b1011 4
b10 5
17
#250000
0!
00
#255000
1!
0#
0$
b0 %
b0 &
10
02
03
b0 4
b0 5
b1100 I
b1101 J
#260000
0!
00
#265000
1!
1#
1$
b1100 %
b1101 &
10
12
13
b1100 4
b1101 5
17
#270000
0!
00
#275000
1!
0#
0$
b0 %
b0 &
10
02
03
b0 4
b0 5
b1101 I
b1001 J
#280000
0!
00
#285000
1!
1#
1$
b1101 %
b1001 &
10
12
13
b1101 4
b1001 5
17
#290000
0!
00
#295000
1!
0#
0$
b0 %
b0 &
10
02
03
b0 4
b0 5
b1110 I
b1110 J
#300000
0!
00
#305000
1!
1#
1$
b1110 %
b1110 &
10
12
13
b1110 4
b1110 5
17
#310000
0!
00
#315000
1!
0#
0$
b0 %
b0 &
10
02
03
b0 4
b0 5
b1111 I
b1100 J
#320000
0!
00
#325000
1!
1#
1$
b1111 %
b1100 &
10
12
13
b1111 4
b1100 5
17
#330000
0!
00
#335000
1!
0#
0$
b0 %
b0 &
b11010100100100 -
10
02
03
b0 4
b0 5
b11010100100100 <
1>
b1 A
b1 B
#340000
0!
00
#345000
1!
10
b10000 =
0>
b1111 ?
b1 @
b10 A
b10 B
#350000
0!
00
#355000
1!
b1 *
1+
10
b1 9
1:
1>
b11 A
b11 B
#360000
0!
00
#365000
1!
b0 *
0+
10
b0 9
0:
b11 B
#370000
0!
00
#375000
1!
10
b0 9
0:
b11 B
#380000
0!
00
#385000
1!
1,
b11010100100100 -
10
b0 9
0:
1;
b1 A
b1 B
#390000
0!
00
#395000
1!
0,
10
0;
b10000 =
0>
b1111 ?
b1 @
b10 A
b10 B
#400000
0!
00
#405000
1!
b1 *
1+
10
b1 9
1:
1>
b11 A
b11 B
#410000
0!
00
#415000
1!
b0 *
0+
10
b0 9
0:
b11 B
#420000
0!
00
#425000
1!
10
b0 9
0:
b11 B
#430000
0!
00
#435000
1!
1,
b11010100100100 -
10
b0 9
0:
1;
b1 A
b1 B
#440000
0!
00
#445000
1!
0,
10
0;
b10000 =
0>
b1111 ?
b1 @
b10 A
b10 B
#450000
0!
00
#455000
1!
b1 *
1+
10
b1 9
1:
1>
b11 A
b11 B
#460000
0!
00
#465000
1!
b0 *
0+
10
b0 9
0:
b11 B
#470000
0!
00
#475000
1!
10
b0 9
0:
b11 B
#480000
0!
00
#485000
1!
1,
b11010100100100 -
10
b0 9
0:
1;
b1 A
b1 B
#490000
0!
00
#495000
1!
0,
10
0;
b10000 =
0>
b1111 ?
b1 @
b10 A
b10 B
#500000
0!
00
#505000
1!
b1 *
1+
10
b1 9
1:
1>
b11 A
b11 B
#510000
0!
00
#515000
1!
b0 *
0+
10
b0 9
0:
b11 B
#520000
0!
00
#525000
1!
10
b0 9
0:
b11 B
#530000
0!
00
#535000
1!
1,
b11010100100100 -
10
b0 9
0:
1;
b1 A
b1 B
#540000
0!
00
#545000
1!
0,
10
0;
b10000 =
0>
b1111 ?
b1 @
b10 A
b10 B
#550000
0!
00
#555000
1!
b1 *
1+
10
b1 9
1:
1>
b11 A
b11 B
#560000
0!
00
#565000
1!
b0 *
0+
10
b0 9
0:
b11 B
#570000
0!
00
#575000
1!
10
b0 9
0:
b11 B
#580000
0!
00
#585000
1!
1,
b11010100100100 -
10
b0 9
0:
1;
b1 A
b1 B
#590000
0!
00
#595000
1!
0,
10
0;
b10000 =
0>
b1111 ?
b1 @
b10 A
b10 B
#600000
0!
00
#605000
1!
b1 *
1+
10
b1 9
1:
1>
b11 A
b11 B
#610000
0!
00
#615000
1!
b0 *
0+
10
b0 9
0:
b11 B
#620000
0!
00
#625000
1!
10
b0 9
0:
b11 B
#630000
0!
00
#635000
1!
1,
b11010100100100 -
10
b0 9
0:
1;
b1 A
b1 B
#640000
0!
00
#645000
1!
0,
10
0;
b10000 =
0>
b1111 ?
b1 @
b10 A
b10 B
#650000
0!
00
#655000
1!
b1 *
1+
10
b1 9
1:
1>
b11 A
b11 B
#660000
0!
00
#665000
1!
b0 *
0+
10
b0 9
0:
b11 B
#670000
0!
00
#675000
1!
10
b0 9
0:
b11 B
#680000
0!
00
#685000
1!
1,
b11010100100100 -
10
b0 9
0:
1;
b1 A
b1 B
#690000
0!
00
#695000
1!
0,
10
0;
b10000 =
0>
b1111 ?
b1 @
b10 A
b10 B
#700000
0!
00
#705000
1!
b1 *
1+
10
b1 9
1:
1>
b11 A
b11 B
#710000
0!
00
#715000
1!
b0 *
0+
10
b0 9
0:
b11 B
#720000
0!
00
#725000
1!
10
b0 9
0:
b11 B
#730000
0!
00
#735000
1!
1,
b11010100100100 -
10
b0 9
0:
1;
b1 A
b1 B
#740000
0!
00
#745000
1!
0,
10
0;
b10000 =
0>
b1111 ?
b1 @
b10 A
b10 B
#750000
0!
00
#755000
1!
b1 *
1+
10
b1 9
1:
1>
b11 A
b11 B
#760000
0!
00
#765000
1!
b0 *
0+
10
b0 9
0:
b11 B
#770000
0!
00
#775000
1!
10
b0 9
0:
b11 B
#780000
0!
00
#785000
1!
1,
b11010100100100 -
10
b0 9
0:
1;
b1 A
b1 B
#790000
0!
00
#795000
1!
0,
10
0;
b10000 =
0>
b1111 ?
b1 @
b10 A
b10 B
#800000
0!
00
#805000
1!
b1 *
1+
10
b1 9
1:
1>
b11 A
b11 B
#810000
0!
00
#815000
1!
b0 *
0+
10
b0 9
0:
b11 B
#820000
0!
00
#825000
1!
10
b0 9
0:
b11 B
#830000
0!
00
#835000
1!
1,
b11010100100100 -
10
b0 9
0:
1;
b1 A
b1 B
#840000
0!
00
#845000
1!
0,
10
0;
b10000 =
0>
b1111 ?
b1 @
b10 A
b10 B
#850000
0!
00
#855000
1!
b1 *
1+
10
b1 9
1:
1>
b11 A
b11 B
#860000
0!
00
#865000
1!
b0 *
0+
10
b0 9
0:
b11 B
#870000
0!
00
#875000
1!
10
b0 9
0:
b11 B
#880000
0!
00
#885000
1!
1,
b11010100100100 -
10
b0 9
0:
1;
b1 A
b1 B
#890000
0!
00
#895000
1!
0,
10
0;
b10000 =
0>
b1111 ?
b1 @
b10 A
b10 B
#900000
0!
00
#905000
1!
b1 *
1+
10
b1 9
1:
1>
b11 A
b11 B
#910000
0!
00
#915000
1!
b0 *
0+
10
b0 9
0:
b11 B
#920000
0!
00
#925000
1!
10
b0 9
0:
b11 B
#930000
0!
00
#935000
1!
1,
b11010100100100 -
10
b0 9
0:
1;
b1 A
b1 B
#940000
0!
00
#945000
1!
0,
10
0;
b10000 =
0>
b1111 ?
b1 @
b10 A
b10 B
#950000
0!
00
#955000
1!
b1 *
1+
10
b1 9
1:
1>
b11 A
b11 B
#960000
0!
00
#965000
1!
b0 *
0+
10
b0 9
0:
b11 B
#970000
0!
00
#975000
1!
10
b0 9
0:
b11 B
#980000
0!
00
#985000
1!
1,
b11010100100100 -
10
b0 9
0:
1;
b1 A
b1 B
#990000
0!
00
#995000
1!
0,
10
0;
b10000 =
0>
b1111 ?
b1 @
b10 A
b10 B
