Watchdog Timer/design.sv
module watchdog_timer(
  //Processor
  pclk_i,prst_i,paddr_i,pwdata_i,prdata_o,pwrite_i,penable_i,pready_o,pslverr_o,
  //System Interface
  activity_i,sys_reset_o
);
  
  parameter S_RESET 			= 2'b00;
  parameter S_NO_ACTIVITY 		= 2'b01;
  parameter S_ACTIVITY 			= 2'b10;
  parameter S_THRESHOLD_TIMEOUT = 2'b11;
  
  input pclk_i,prst_i,pwrite_i,penable_i;
  input [7:0] paddr_i;
  input [7:0] pwdata_i;
  output reg [7:0] prdata_o;
  output reg pready_o;
  output reg pslverr_o;
  input activity_i;
  output reg sys_reset_o;
 
  integer no_activity_count;
  
  //Register to store the threshold value of the timer
  reg [7:0] threshold_timer_reg; //1 register
  
  //For State Machine to be implemented
  reg [2:0] state, next_state;
  
  always @(next_state) begin
    state = next_state;
  end
  
  //Process 1 - Programming the registers
  always @(posedge pclk_i) begin
    
    if(prst_i == 1) begin
      //Reset all the reg variables
      prdata_o = 0;
      pready_o = 0;
      pslverr_o = 0;
      state = S_RESET;
      next_state = S_RESET;
      sys_reset_o = 0;
      no_activity_count = 0;
    end
    
    else begin
      if (penable_i == 1) begin
        pready_o = 1;
        if(pwrite_i == 1) begin
          threshold_timer_reg = pwdata_i;
        end
        else begin
          prdata_o = threshold_timer_reg;
        end
      end
    end
  end
  
  //Process 2 - Implementing Watchdog Timer Functionality
  always @(posedge pclk_i) begin
    case(state)
  
      S_RESET: begin
        sys_reset_o = 0;
        if (activity_i == 1) begin
          next_state = S_ACTIVITY;
        end
        else begin
          next_state = S_NO_ACTIVITY;
          no_activity_count = no_activity_count + 1;
        end
      end
      
      S_NO_ACTIVITY: begin
        sys_reset_o = 0;
        if (activity_i == 0) begin
          no_activity_count = no_activity_count + 1;
          if(no_activity_count == threshold_timer_reg) begin
            next_state = S_THRESHOLD_TIMEOUT;
          end
        end
        else begin
          next_state = S_ACTIVITY;
        end
      end
      
      S_ACTIVITY: begin
        sys_reset_o = 0;
        no_activity_count = 0;
        if (activity_i == 1) begin
          next_state = S_ACTIVITY;
        end
        else begin
          next_state = S_NO_ACTIVITY;
        end
      end
      
      S_THRESHOLD_TIMEOUT: begin
        sys_reset_o = 1;
        next_state = S_NO_ACTIVITY;
        no_activity_count = 0;
      end
      
    endcase
  end
  
  
endmodule

Watchdog Timer/testbench.sv
module tb_watchdog_timer;
  
  reg pclk_i,prst_i,pwrite_i,penable_i;
  reg [7:0] paddr_i;
  reg [7:0] pwdata_i;
  reg activity_i;
  wire [7:0] prdata_o;
  wire pready_o;
  wire pslverr_o;
  wire sys_reset_o;
  
  watchdog_timer dut(
  //Processor
  pclk_i,prst_i,paddr_i,pwdata_i,prdata_o,pwrite_i,penable_i,pready_o,pslverr_o,
  //System Interface
  activity_i,sys_reset_o
);
  
  initial begin
    pclk_i = 0;
    forever #5 pclk_i = ~pclk_i;
  end
  
  initial begin
    prst_i = 1;
    activity_i = 0;
    paddr_i = 0;
    pwrite_i = 0;
    pwdata_i = 0;
    penable_i = 0;
    repeat(2) @(posedge pclk_i);
    prst_i = 0;
    
    //Program Register
    reg_write(0,200);
    #2000;
    activity_i = 1;
    #10;
    activity_i = 0;
    #1000;
    activity_i = 1;
    #3000;
    $finish;
  end
  
  task reg_write(input [7:0] addr, input [7:0] data);
    begin
      @(posedge pclk_i);
      paddr_i = addr;
      pwdata_i = data; //(i: giving Lowest Priority and 15-i: giving Highest Priority) (Can't use $random -> same priority might be assigned)
      pwrite_i = 1;
      penable_i = 1;
      wait (pready_o == 1);
      @(posedge pclk_i);
      pwrite_i = 0;
      penable_i = 0;
      paddr_i = 0;
      pwdata_i = 0;
    end
  endtask
  
  initial begin
    $dumpfile("intc.vcd");
    $dumpvars(0,tb_watchdog_timer);
  end
endmodule

Watchdog Timer/Watchdog Timer.sim/sim_1/behav/xsim/intc.vcd
$date
   Sun Jan 24 19:26:25 2021
$end
$version
  2020.1
$end
$timescale
  1ps
$end
$scope module tb_watchdog_timer $end
$var reg 1 ! pclk_i $end
$var reg 1 " prst_i $end
$var reg 1 # pwrite_i $end
$var reg 1 $ penable_i $end
$var reg 8 % paddr_i [7:0] $end
$var reg 8 & pwdata_i [7:0] $end
$var reg 1 ' activity_i $end
$var wire 8 ( prdata_o [7:0] $end
$var wire 1 ) pready_o $end
$var wire 1 * pslverr_o $end
$var wire 1 + sys_reset_o $end
$scope module dut $end
$var wire 1 , pclk_i $end
$var wire 1 - prst_i $end
$var wire 1 . pwrite_i $end
$var wire 1 / penable_i $end
$var wire 8 0 paddr_i [7:0] $end
$var wire 8 1 pwdata_i [7:0] $end
$var reg 8 2 prdata_o [7:0] $end
$var reg 1 3 pready_o $end
$var reg 1 4 pslverr_o $end
$var wire 1 5 activity_i $end
$var reg 1 6 sys_reset_o $end
$var integer 32 7 no_activity_count $end
$var reg 8 8 threshold_timer_reg [7:0] $end
$var reg 3 9 state [2:0] $end
$var reg 3 : next_state [2:0] $end
$var parameter 2 ; S_RESET [1:0] $end
$var parameter 2 < S_NO_ACTIVITY [1:0] $end
$var parameter 2 = S_ACTIVITY [1:0] $end
$var parameter 2 > S_THRESHOLD_TIMEOUT [1:0] $end
$upscope $end
$scope task reg_write $end
$var reg 8 ? addr [7:0] $end
$var reg 8 @ data [7:0] $end
$upscope $end
$upscope $end
$enddefinitions $end
#0
$dumpvars
0!
1"
0#
0$
b0 %
b0 &
0'
bx (
x)
x*
x+
0,
1-
0.
0/
b0 0
b0 1
bx 2
x3
x4
05
x6
bx 7
bx 8
bx 9
bx :
b0 ;
b1 <
b10 =
b11 >
bx ?
bx @
$end
#5000
1!
b0 (
0)
0*
0+
1,
b0 2
03
04
06
b1 7
b1 9
b1 :
#10000
0!
0,
#15000
1!
0"
1,
0-
06
b10 7
b0 ?
b11001000 @
#20000
0!
0,
#25000
1!
1#
1$
b0 %
b11001000 &
1)
1,
1.
1/
b11001000 1
13
06
b11 7
b11001000 8
#30000
0!
0,
#35000
1!
0#
0$
b0 %
b0 &
1,
0.
0/
b0 1
06
b100 7
#40000
0!
0,
#45000
1!
1,
06
b101 7
#50000
0!
0,
#55000
1!
1,
06
b110 7
#60000
0!
0,
#65000
1!
1,
06
b111 7
#70000
0!
0,
#75000
1!
1,
06
b1000 7
#80000
0!
0,
#85000
1!
1,
06
b1001 7
#90000
0!
0,
#95000
1!
1,
06
b1010 7
#100000
0!
0,
#105000
1!
1,
06
b1011 7
#110000
0!
0,
#115000
1!
1,
06
b1100 7
#120000
0!
0,
#125000
1!
1,
06
b1101 7
#130000
0!
0,
#135000
1!
1,
06
b1110 7
#140000
0!
0,
#145000
1!
1,
06
b1111 7
#150000
0!
0,
#155000
1!
1,
06
b10000 7
#160000
0!
0,
#165000
1!
1,
06
b10001 7
#170000
0!
0,
#175000
1!
1,
06
b10010 7
#180000
0!
0,
#185000
1!
1,
06
b10011 7
#190000
0!
0,
#195000
1!
1,
06
b10100 7
#200000
0!
0,
#205000
1!
1,
06
b10101 7
#210000
0!
0,
#215000
1!
1,
06
b10110 7
#220000
0!
0,
#225000
1!
1,
06
b10111 7
#230000
0!
0,
#235000
1!
1,
06
b11000 7
#240000
0!
0,
#245000
1!
1,
06
b11001 7
#250000
0!
0,
#255000
1!
1,
06
b11010 7
#260000
0!
0,
#265000
1!
1,
06
b11011 7
#270000
0!
0,
#275000
1!
1,
06
b11100 7
#280000
0!
0,
#285000
1!
1,
06
b11101 7
#290000
0!
0,
#295000
1!
1,
06
b11110 7
#300000
0!
0,
#305000
1!
1,
06
b11111 7
#310000
0!
0,
#315000
1!
1,
06
b100000 7
#320000
0!
0,
#325000
1!
1,
06
b100001 7
#330000
0!
0,
#335000
1!
1,
06
b100010 7
#340000
0!
0,
#345000
1!
1,
06
b100011 7
#350000
0!
0,
#355000
1!
1,
06
b100100 7
#360000
0!
0,
#365000
1!
1,
06
b100101 7
#370000
0!
0,
#375000
1!
1,
06
b100110 7
#380000
0!
0,
#385000
1!
1,
06
b100111 7
#390000
0!
0,
#395000
1!
1,
06
b101000 7
#400000
0!
0,
#405000
1!
1,
06
b101001 7
#410000
0!
0,
#415000
1!
1,
06
b101010 7
#420000
0!
0,
#425000
1!
1,
06
b101011 7
#430000
0!
0,
#435000
1!
1,
06
b101100 7
#440000
0!
0,
#445000
1!
1,
06
b101101 7
#450000
0!
0,
#455000
1!
1,
06
b101110 7
#460000
0!
0,
#465000
1!
1,
06
b101111 7
#470000
0!
0,
#475000
1!
1,
06
b110000 7
#480000
0!
0,
#485000
1!
1,
06
b110001 7
#490000
0!
0,
#495000
1!
1,
06
b110010 7
#500000
0!
0,
#505000
1!
1,
06
b110011 7
#510000
0!
0,
#515000
1!
1,
06
b110100 7
#520000
0!
0,
#525000
1!
1,
06
b110101 7
#530000
0!
0,
#535000
1!
1,
06
b110110 7
#540000
0!
0,
#545000
1!
1,
06
b110111 7
#550000
0!
0,
#555000
1!
1,
06
b111000 7
#560000
0!
0,
#565000
1!
1,
06
b111001 7
#570000
0!
0,
#575000
1!
1,
06
b111010 7
#580000
0!
0,
#585000
1!
1,
06
b111011 7
#590000
0!
0,
#595000
1!
1,
06
b111100 7
#600000
0!
0,
#605000
1!
1,
06
b111101 7
#610000
0!
0,
#615000
1!
1,
06
b111110 7
#620000
0!
0,
#625000
1!
1,
06
b111111 7
#630000
0!
0,
#635000
1!
1,
06
b1000000 7
#640000
0!
0,
#645000
1!
1,
06
b1000001 7
#650000
0!
0,
#655000
1!
1,
06
b1000010 7
#660000
0!
0,
#665000
1!
1,
06
b1000011 7
#670000
0!
0,
#675000
1!
1,
06
b1000100 7
#680000
0!
0,
#685000
1!
1,
06
b1000101 7
#690000
0!
0,
#695000
1!
1,
06
b1000110 7
#700000
0!
0,
#705000
1!
1,
06
b1000111 7
#710000
0!
0,
#715000
1!
1,
06
b1001000 7
#720000
0!
0,
#725000
1!
1,
06
b1001001 7
#730000
0!
0,
#735000
1!
1,
06
b1001010 7
#740000
0!
0,
#745000
1!
1,
06
b1001011 7
#750000
0!
0,
#755000
1!
1,
06
b1001100 7
#760000
0!
0,
#765000
1!
1,
06
b1001101 7
#770000
0!
0,
#775000
1!
1,
06
b1001110 7
#780000
0!
0,
#785000
1!
1,
06
b1001111 7
#790000
0!
0,
#795000
1!
1,
06
b1010000 7
#800000
0!
0,
#805000
1!
1,
06
b1010001 7
#810000
0!
0,
#815000
1!
1,
06
b1010010 7
#820000
0!
0,
#825000
1!
1,
06
b1010011 7
#830000
0!
0,
#835000
1!
1,
06
b1010100 7
#840000
0!
0,
#845000
1!
1,
06
b1010101 7
#850000
0!
0,
#855000
1!
1,
06
b1010110 7
#860000
0!
0,
#865000
1!
1,
06
b1010111 7
#870000
0!
0,
#875000
1!
1,
06
b1011000 7
#880000
0!
0,
#885000
1!
1,
06
b1011001 7
#890000
0!
0,
#895000
1!
1,
06
b1011010 7
#900000
0!
0,
#905000
1!
1,
06
b1011011 7
#910000
0!
0,
#915000
1!
1,
06
b1011100 7
#920000
0!
0,
#925000
1!
1,
06
b1011101 7
#930000
0!
0,
#935000
1!
1,
06
b1011110 7
#940000
0!
0,
#945000
1!
1,
06
b1011111 7
#950000
0!
0,
#955000
1!
1,
06
b1100000 7
#960000
0!
0,
#965000
1!
1,
06
b1100001 7
#970000
0!
0,
#975000
1!
1,
06
b1100010 7
#980000
0!
0,
#985000
1!
1,
06
b1100011 7
#990000
0!
0,
#995000
1!
1,
06
b1100100 7
