Interrupt Controller/design.sv
module interrupt_controller(
  //Processor
  pclk_i,prst_i,paddr_i,pwdata_i,prdata_o,pwrite_i,penable_i,pready_o,pslverr_o,
  intr_to_service_o,intr_valid_o,intr_serviced_i,
  //Peripheral Controllers
  intr_active_i
);
  
  //penable_i is given by processor
  //pready_o is given by Interrupt Controller
  
  parameter NUM_INTR 		= 16;
  parameter S_NO_INTR 		= 3'b000;
  parameter S_INTR_ACTIVE 	= 3'b001;
  parameter S_INTR_GIVEN_TO_PROC = 3'b010;
  parameter S_INTR_SERVICED = 3'b011;
  parameter S_INTR_ERROR 		= 3'b100;
  
  input pclk_i,prst_i,pwrite_i,penable_i;
  input [7:0] paddr_i;
  input [7:0] pwdata_i;
  output reg [7:0] prdata_o;
  output reg pready_o;
  output reg pslverr_o;
  output reg [3:0] intr_to_service_o;
  output reg intr_valid_o;
  input intr_serviced_i;
  input [NUM_INTR-1:0] intr_active_i;
  
  integer i;
  reg first_match_f;
  reg [3:0] highest_priority;
  reg [3:0] intr_with_highest_prio;
  
  //Array to registers to decide the prioroty of the interrupts by the processor
  reg [7:0] priority_regA[NUM_INTR-1:0]; //16 registers
  
  //For State Machine to be implemented
  reg [2:0] state, next_state;
  
  always @(next_state) begin
    state = next_state;
  end
  
  //Process 1 - Programming (writing the priority and reading) the registers
  always @(posedge pclk_i) begin
    
    if(prst_i == 1) begin
      //Reset all the reg variables
      prdata_o = 0;
      pready_o = 0;
      pslverr_o = 0;
      intr_to_service_o = 0;
      intr_valid_o = 0;
      first_match_f = 0;
      highest_priority = 0;
      intr_with_highest_prio = 0;
      for (i=0 ; i<NUM_INTR ; i=i+1) begin
        priority_regA[i] = 0;
      end
      state = S_NO_INTR;
      next_state = S_NO_INTR;
    end
    
    else begin
      if (penable_i == 1) begin
        pready_o = 1;
        if(pwrite_i == 1) begin
          priority_regA[paddr_i] = pwdata_i;
        end
        else begin
          prdata_o = priority_regA[paddr_i];
        end
      end
    end
  end
  
  //Process 2 - Interrupt Handling: Actual functionality of Interrupt Controller
  //Interrupt Handling is implemented by STATE MACHINES
  always @(posedge pclk_i) begin
    case(state)
      
      S_NO_INTR: begin
        if(intr_active_i != 0) begin
          next_state = S_INTR_ACTIVE;
          first_match_f = 1;
        end
      end
      
      S_INTR_ACTIVE: begin
        //Figure out the highest priority interrupt amongst all the active interrupts
        for (i=0 ; i<NUM_INTR ; i=i+1) begin
          if (intr_active_i != 0) begin
            if (first_match_f == 1) begin
              highest_priority = priority_regA[i];
              intr_with_highest_prio = i;
              first_match_f = 0; //One time only to get the reference value
            end
            else begin
              if (highest_priority < priority_regA[i]) begin
                highest_priority = priority_regA[i];
                intr_with_highest_prio = i;
              end
            end
          end
        end
        next_state = S_INTR_GIVEN_TO_PROC;
      end
      
      S_INTR_GIVEN_TO_PROC: begin
        intr_to_service_o = intr_with_highest_prio;
        intr_valid_o = 1;
        first_match_f = 1;
        next_state = S_INTR_SERVICED;
      end
      
      S_INTR_SERVICED: begin
        if (intr_serviced_i == 1) begin
          intr_to_service_o = 0;
          intr_valid_o = 0;
          if (intr_active_i != 0) begin
            next_state = S_INTR_ACTIVE;
          end
          else begin
            next_state = S_NO_INTR;
          end
        end
        else begin
          next_state = S_INTR_SERVICED;
        end
      end
      
      S_INTR_ERROR: begin
        //Will be implemented later
      end
      
    endcase
  end
  
  
endmodule

Interrupt Controller/testbench.sv
module tb_INTC;
  
  parameter NUM_INTR = 16;
  
  reg pclk_i,prst_i,pwrite_i,penable_i;
  reg [7:0] paddr_i;
  reg [7:0] pwdata_i;
  wire [7:0] prdata_o;
  wire pready_o;
  wire pslverr_o;
  wire [3:0] intr_to_service_o;
  wire intr_valid_o;
  reg intr_serviced_i;
  reg [NUM_INTR-1:0] intr_active_i;
  
  integer i;
  
  interrupt_controller dut (
    //Processor
    pclk_i,prst_i,paddr_i,pwdata_i,prdata_o,pwrite_i,penable_i,pready_o,pslverr_o,
    intr_to_service_o,intr_valid_o,intr_serviced_i,
    //Peripheral Controllers
    intr_active_i
	);
  
  initial begin
    pclk_i = 0;
    forever #5 pclk_i = ~pclk_i;
  end
  
  initial begin
    prst_i = 1;
    intr_active_i = 0;
    paddr_i = 0;
    pwrite_i = 0;
    pwdata_i = 0;
    penable_i = 0;
    repeat(2) @(posedge pclk_i);
    prst_i = 0;
    
    //Apply stimulus
    //Step1: Program the priority registers
    /*for(i=0 ; i<NUM_INTR ; i=i+1) begin
      //reg_write(i,i); //LOWEST Priority
      reg_write(i,NUM_INTR-1-i); //HIGHEST Priority
    end*/
    //For random priority generation
    reg_write(0,10);
    reg_write(1,15);
    reg_write(2,7);
    reg_write(3,5);
    reg_write(4,6);
    reg_write(5,3);
    reg_write(6,8);
    reg_write(7,4);
    reg_write(8,0);
    reg_write(9,1);
    reg_write(10,11);
    reg_write(11,2);
    reg_write(12,13);
    reg_write(13,9);
    reg_write(14,14);
    reg_write(15,12);
    
    //To generate interrupts
    intr_active_i = $random;
    #100;
    intr_active_i = intr_active_i | $random;
    #1000;
    intr_active_i = intr_active_i | $random;
    #2000;
    $finish;
    
  end
  
  //Service the interrupt
  initial begin
    forever begin
      @(posedge pclk_i);
      if(intr_valid_o == 1) begin
        //Take some time to service the interrupt
        #20;
        //Drop the interrupt once it is being serviced
        intr_active_i[intr_to_service_o] = 0; //Dropping the interrupt
        intr_serviced_i = 1;
        #10;
        intr_serviced_i = 0;
      end
    end
  end
  
  task reg_write(input [7:0] addr, input [7:0] data);
    begin
      @(posedge pclk_i);
      paddr_i = addr;
      pwdata_i = data; //(i: giving Lowest Priority and 15-i: giving Highest Priority) (Can't use $random -> same priority might be assigned)
      pwrite_i = 1;
      penable_i = 1;
      wait (pready_o == 1);
      @(posedge pclk_i);
      pwrite_i = 0;
      penable_i = 0;
      paddr_i = 0;
      pwdata_i = 0;
    end
  endtask
  
  initial begin
    $dumpfile("intc.vcd");
    $dumpvars(0,tb_INTC);
  end
endmodule

Interrupt Controller/intc.vcd
$date
	Sun Jan 24 18:18:40 2021
$end
$version
	Icarus Verilog
$end
$timescale
	1s
$end
$scope module tb_INTC $end
$var wire 4 ! intr_to_service_o [3:0] $end
$var wire 1 " intr_valid_o $end
$var wire 8 # prdata_o [7:0] $end
$var wire 1 $ pready_o $end
$var wire 1 % pslverr_o $end
$var reg 16 & intr_active_i [15:0] $end
$var reg 1 ' intr_serviced_i $end
$var reg 8 ( paddr_i [7:0] $end
$var reg 1 ) pclk_i $end
$var reg 1 * penable_i $end
$var reg 1 + prst_i $end
$var reg 8 , pwdata_i [7:0] $end
$var reg 1 - pwrite_i $end
$scope module dut $end
$var wire 16 . intr_active_i [15:0] $end
$var wire 1 / intr_serviced_i $end
$var wire 8 0 paddr_i [7:0] $end
$var wire 1 1 pclk_i $end
$var wire 1 2 penable_i $end
$var wire 1 3 prst_i $end
$var wire 8 4 pwdata_i [7:0] $end
$var wire 1 5 pwrite_i $end
$var reg 1 6 first_match_f $end
$var reg 4 7 highest_priority [3:0] $end
$var integer 32 8 i [31:0] $end
$var reg 4 9 intr_to_service_o [3:0] $end
$var reg 1 : intr_valid_o $end
$var reg 4 ; intr_with_highest_prio [3:0] $end
$var reg 3 < next_state [2:0] $end
$var reg 8 = prdata_o [7:0] $end
$var reg 1 > pready_o $end
$var reg 1 ? pslverr_o $end
$var reg 3 @ state [2:0] $end
$upscope $end
$scope task reg_write $end
$var reg 8 A addr [7:0] $end
$var reg 8 B data [7:0] $end
$upscope $end
$upscope $end
$enddefinitions $end
#0
$dumpvars
bx B
bx A
bx @
x?
x>
bx =
bx <
bx ;
x:
bx 9
bx 8
bx 7
x6
05
b0 4
13
02
01
b0 0
x/
b0 .
0-
b0 ,
1+
0*
0)
b0 (
x'
b0 &
x%
x$
bx #
x"
bx !
$end
#5
b0 <
b0 @
b10000 8
b0 ;
b0 7
06
0:
0"
b0 9
b0 !
0?
0%
0>
0$
b0 =
b0 #
1)
11
#10
0)
01
#15
b1010 B
b0 A
0+
03
b10000 8
1)
11
#20
0)
01
#25
1>
1$
1*
12
1-
15
b1010 ,
b1010 4
1)
11
#30
0)
01
#35
b1111 B
b1 A
b0 ,
b0 4
0*
02
0-
05
1)
11
#40
0)
01
#45
1*
12
1-
15
b1111 ,
b1111 4
b1 (
b1 0
1)
11
#50
0)
01
#55
b111 B
b10 A
b0 ,
b0 4
b0 (
b0 0
0*
02
0-
05
1)
11
#60
0)
01
#65
1*
12
1-
15
b111 ,
b111 4
b10 (
b10 0
1)
11
#70
0)
01
#75
b101 B
b11 A
b0 ,
b0 4
b0 (
b0 0
0*
02
0-
05
1)
11
#80
0)
01
#85
1*
12
1-
15
b101 ,
b101 4
b11 (
b11 0
1)
11
#90
0)
01
#95
b110 B
b100 A
b0 ,
b0 4
b0 (
b0 0
0*
02
0-
05
1)
11
#100
0)
01
#105
1*
12
1-
15
b110 ,
b110 4
b100 (
b100 0
1)
11
#110
0)
01
#115
b11 B
b101 A
b0 ,
b0 4
b0 (
b0 0
0*
02
0-
05
1)
11
#120
0)
01
#125
1*
12
1-
15
b11 ,
b11 4
b101 (
b101 0
1)
11
#130
0)
01
#135
b1000 B
b110 A
b0 ,
b0 4
b0 (
b0 0
0*
02
0-
05
1)
11
#140
0)
01
#145
1*
12
1-
15
b1000 ,
b1000 4
b110 (
b110 0
1)
11
#150
0)
01
#155
b100 B
b111 A
b0 ,
b0 4
b0 (
b0 0
0*
02
0-
05
1)
11
#160
0)
01
#165
1*
12
1-
15
b100 ,
b100 4
b111 (
b111 0
1)
11
#170
0)
01
#175
b0 B
b1000 A
b0 ,
b0 4
b0 (
b0 0
0*
02
0-
05
1)
11
#180
0)
01
#185
1*
12
1-
15
b1000 (
b1000 0
1)
11
#190
0)
01
#195
b1 B
b1001 A
b0 (
b0 0
0*
02
0-
05
1)
11
#200
0)
01
#205
1*
12
1-
15
b1 ,
b1 4
b1001 (
b1001 0
1)
11
#210
0)
01
#215
b1011 B
b1010 A
b0 ,
b0 4
b0 (
b0 0
0*
02
0-
05
1)
11
#220
0)
01
#225
1*
12
1-
15
b1011 ,
b1011 4
b1010 (
b1010 0
1)
11
#230
0)
01
#235
b10 B
b1011 A
b0 ,
b0 4
b0 (
b0 0
0*
02
0-
05
1)
11
#240
0)
01
#245
1*
12
1-
15
b10 ,
b10 4
b1011 (
b1011 0
1)
11
#250
0)
01
#255
b1101 B
b1100 A
b0 ,
b0 4
b0 (
b0 0
0*
02
0-
05
1)
11
#260
0)
01
#265
1*
12
1-
15
b1101 ,
b1101 4
b1100 (
b1100 0
1)
11
#270
0)
01
#275
b1001 B
b1101 A
b0 ,
b0 4
b0 (
b0 0
0*
02
0-
05
1)
11
#280
0)
01
#285
1*
12
1-
15
b1001 ,
b1001 4
b1101 (
b1101 0
1)
11
#290
0)
01
#295
b1110 B
b1110 A
b0 ,
b0 4
b0 (
b0 0
0*
02
0-
05
1)
11
#300
0)
01
#305
1*
12
1-
15
b1110 ,
b1110 4
b1110 (
b1110 0
1)
11
#310
0)
01
#315
b1100 B
b1111 A
b0 ,
b0 4
b0 (
b0 0
0*
02
0-
05
1)
11
#320
0)
01
#325
1*
12
1-
15
b1100 ,
b1100 4
b1111 (
b1111 0
1)
11
#330
0)
01
#335
b11010100100100 &
b11010100100100 .
b0 ,
b0 4
b0 (
b0 0
0*
02
0-
05
1)
11
#340
0)
01
#345
b1 @
16
b1 <
1)
11
#350
0)
01
#355
b10 @
b10 <
b1 ;
06
b1111 7
b10000 8
1)
11
#360
0)
01
#365
b11 @
b11 <
16
1:
1"
b1 9
b1 !
1)
11
#370
0)
01
#375
1)
11
#380
0)
01
#385
1)
11
#390
0)
01
#395
b1 @
b1 <
0:
0"
b0 9
b0 !
1)
11
1'
1/
b11010100100100 &
#400
0)
01
#405
b10 @
b10 <
06
b1 ;
b1111 7
b10000 8
1)
11
0'
0/
#410
0)
01
#415
b11 @
b11 <
16
1:
1"
b1 9
b1 !
1)
11
#420
0)
01
#425
1)
11
#430
0)
01
#435
b1 @
b1 <
0:
0"
b0 9
b0 !
1)
11
1'
1/
b111111110100101 &
b111111110100101 .
#440
0)
01
#445
b10 @
b10 <
06
b1 ;
b1111 7
b10000 8
1)
11
0'
0/
#450
0)
01
#455
b11 @
b11 <
16
1:
1"
b1 9
b1 !
1)
11
#460
0)
01
#465
1)
11
#470
0)
01
#475
b1 @
b1 <
0:
0"
b0 9
b0 !
1)
11
1'
1/
b111111110100101 &
#480
0)
01
#485
b10 @
b10 <
06
b1 ;
b1111 7
b10000 8
1)
11
0'
0/
#490
0)
01
#495
b11 @
b11 <
16
1:
1"
b1 9
b1 !
1)
11
#500
0)
01
#505
1)
11
#510
0)
01
#515
b1 @
b1 <
0:
0"
b0 9
b0 !
1)
11
1'
1/
b111111110100101 &
#520
0)
01
#525
b10 @
b10 <
06
b1 ;
b1111 7
b10000 8
1)
11
0'
0/
#530
0)
01
#535
b11 @
b11 <
16
1:
1"
b1 9
b1 !
1)
11
#540
0)
01
#545
1)
11
#550
0)
01
#555
b1 @
b1 <
0:
0"
b0 9
b0 !
1)
11
1'
1/
b111111110100101 &
#560
0)
01
#565
b10 @
b10 <
06
b1 ;
b1111 7
b10000 8
1)
11
0'
0/
#570
0)
01
#575
b11 @
b11 <
16
1:
1"
b1 9
b1 !
1)
11
#580
0)
01
#585
1)
11
#590
0)
01
#595
b1 @
b1 <
0:
0"
b0 9
b0 !
1)
11
1'
1/
b111111110100101 &
#600
0)
01
#605
b10 @
b10 <
06
b1 ;
b1111 7
b10000 8
1)
11
0'
0/
#610
0)
01
#615
b11 @
b11 <
16
1:
1"
b1 9
b1 !
1)
11
#620
0)
01
#625
1)
11
#630
0)
01
#635
b1 @
b1 <
0:
0"
b0 9
b0 !
1)
11
1'
1/
b111111110100101 &
#640
0)
01
#645
b10 @
b10 <
06
b1 ;
b1111 7
b10000 8
1)
11
0'
0/
#650
0)
01
#655
b11 @
b11 <
16
1:
1"
b1 9
b1 !
1)
11
#660
0)
01
#665
1)
11
#670
0)
01
#675
b1 @
b1 <
0:
0"
b0 9
b0 !
1)
11
1'
1/
b111111110100101 &
#680
0)
01
#685
b10 @
b10 <
06
b1 ;
b1111 7
b10000 8
1)
11
0'
0/
#690
0)
01
#695
b11 @
b11 <
16
1:
1"
b1 9
b1 !
1)
11
#700
0)
01
#705
1)
11
#710
0)
01
#715
b1 @
b1 <
0:
0"
b0 9
b0 !
1)
11
1'
1/
b111111110100101 &
#720
0)
01
#725
b10 @
b10 <
06
b1 ;
b1111 7
b10000 8
1)
11
0'
0/
#730
0)
01
#735
b11 @
b11 <
16
1:
1"
b1 9
b1 !
1)
11
#740
0)
01
#745
1)
11
#750
0)
01
#755
b1 @
b1 <
0:
0"
b0 9
b0 !
1)
11
1'
1/
b111111110100101 &
#760
0)
01
#765
b10 @
b10 <
06
b1 ;
b1111 7
b10000 8
1)
11
0'
0/
#770
0)
01
#775
b11 @
b11 <
16
1:
1"
b1 9
b1 !
1)
11
#780
0)
01
#785
1)
11
#790
0)
01
#795
b1 @
b1 <
0:
0"
b0 9
b0 !
1)
11
1'
1/
b111111110100101 &
#800
0)
01
#805
b10 @
b10 <
06
b1 ;
b1111 7
b10000 8
1)
11
0'
0/
#810
0)
01
#815
b11 @
b11 <
16
1:
1"
b1 9
b1 !
1)
11
#820
0)
01
#825
1)
11
#830
0)
01
#835
b1 @
b1 <
0:
0"
b0 9
b0 !
1)
11
1'
1/
b111111110100101 &
#840
0)
01
#845
b10 @
b10 <
06
b1 ;
b1111 7
b10000 8
1)
11
0'
0/
#850
0)
01
#855
b11 @
b11 <
16
1:
1"
b1 9
b1 !
1)
11
#860
0)
01
#865
1)
11
#870
0)
01
#875
b1 @
b1 <
0:
0"
b0 9
b0 !
1)
11
1'
1/
b111111110100101 &
#880
0)
01
#885
b10 @
b10 <
06
b1 ;
b1111 7
b10000 8
1)
11
0'
0/
#890
0)
01
#895
b11 @
b11 <
16
1:
1"
b1 9
b1 !
1)
11
#900
0)
01
#905
1)
11
#910
0)
01
#915
b1 @
b1 <
0:
0"
b0 9
b0 !
1)
11
1'
1/
b111111110100101 &
#920
0)
01
#925
b10 @
b10 <
06
b1 ;
b1111 7
b10000 8
1)
11
0'
0/
#930
0)
01
#935
b11 @
b11 <
16
1:
1"
b1 9
b1 !
1)
11
#940
0)
01
#945
1)
11
#950
0)
01
#955
b1 @
b1 <
0:
0"
b0 9
b0 !
1)
11
1'
1/
b111111110100101 &
#960
0)
01
#965
b10 @
b10 <
06
b1 ;
b1111 7
b10000 8
1)
11
0'
0/
#970
0)
01
#975
b11 @
b11 <
16
1:
1"
b1 9
b1 !
1)
11
#980
0)
01
#985
1)
11
#990
0)
01
#995
b1 @
b1 <
0:
0"
b0 9
b0 !
1)
11
1'
1/
b111111110100101 &
#1000
0)
01
#1005
b10 @
b10 <
06
b1 ;
b1111 7
b10000 8
1)
11
0'
0/
#1010
0)
01
#1015
b11 @
b11 <
16
1:
1"
b1 9
b1 !
1)
11
#1020
0)
01
#1025
1)
11
#1030
0)
01
#1035
b1 @
b1 <
0:
0"
b0 9
b0 !
1)
11
1'
1/
b111111110100101 &
#1040
0)
01
#1045
b10 @
b10 <
06
b1 ;
b1111 7
b10000 8
1)
11
0'
0/
#1050
0)
01
#1055
b11 @
b11 <
16
1:
1"
b1 9
b1 !
1)
11
#1060
0)
01
#1065
1)
11
#1070
0)
01
#1075
b1 @
b1 <
0:
0"
b0 9
b0 !
1)
11
1'
1/
b111111110100101 &
#1080
0)
01
#1085
b10 @
b10 <
06
b1 ;
b1111 7
b10000 8
1)
11
0'
0/
#1090
0)
01
#1095
b11 @
b11 <
16
1:
1"
b1 9
b1 !
1)
11
#1100
0)
01
#1105
1)
11
#1110
0)
01
#1115
b1 @
b1 <
0:
0"
b0 9
b0 !
1)
11
1'
1/
b111111110100101 &
#1120
0)
01
#1125
b10 @
b10 <
06
b1 ;
b1111 7
b10000 8
1)
11
0'
0/
#1130
0)
01
#1135
b11 @
b11 <
16
1:
1"
b1 9
b1 !
1)
11
#1140
0)
01
#1145
1)
11
#1150
0)
01
#1155
b1 @
b1 <
0:
0"
b0 9
b0 !
1)
11
1'
1/
b111111110100101 &
#1160
0)
01
#1165
b10 @
b10 <
06
b1 ;
b1111 7
b10000 8
1)
11
0'
0/
#1170
0)
01
#1175
b11 @
b11 <
16
1:
1"
b1 9
b1 !
1)
11
#1180
0)
01
#1185
1)
11
#1190
0)
01
#1195
b1 @
b1 <
0:
0"
b0 9
b0 !
1)
11
1'
1/
b111111110100101 &
#1200
0)
01
#1205
b10 @
b10 <
06
b1 ;
b1111 7
b10000 8
1)
11
0'
0/
#1210
0)
01
#1215
b11 @
b11 <
16
1:
1"
b1 9
b1 !
1)
11
#1220
0)
01
#1225
1)
11
#1230
0)
01
#1235
b1 @
b1 <
0:
0"
b0 9
b0 !
1)
11
1'
1/
b111111110100101 &
#1240
0)
01
#1245
b10 @
b10 <
06
b1 ;
b1111 7
b10000 8
1)
11
0'
0/
#1250
0)
01
#1255
b11 @
b11 <
16
1:
1"
b1 9
b1 !
1)
11
#1260
0)
01
#1265
1)
11
#1270
0)
01
#1275
b1 @
b1 <
0:
0"
b0 9
b0 !
1)
11
1'
1/
b111111110100101 &
#1280
0)
01
#1285
b10 @
b10 <
06
b1 ;
b1111 7
b10000 8
1)
11
0'
0/
#1290
0)
01
#1295
b11 @
b11 <
16
1:
1"
b1 9
b1 !
1)
11
#1300
0)
01
#1305
1)
11
#1310
0)
01
#1315
b1 @
b1 <
0:
0"
b0 9
b0 !
1)
11
1'
1/
b111111110100101 &
#1320
0)
01
#1325
b10 @
b10 <
06
b1 ;
b1111 7
b10000 8
1)
11
0'
0/
#1330
0)
01
#1335
b11 @
b11 <
16
1:
1"
b1 9
b1 !
1)
11
#1340
0)
01
#1345
1)
11
#1350
0)
01
#1355
b1 @
b1 <
0:
0"
b0 9
b0 !
1)
11
1'
1/
b111111110100101 &
#1360
0)
01
#1365
b10 @
b10 <
06
b1 ;
b1111 7
b10000 8
1)
11
0'
0/
#1370
0)
01
#1375
b11 @
b11 <
16
1:
1"
b1 9
b1 !
1)
11
#1380
0)
01
#1385
1)
11
#1390
0)
01
#1395
b1 @
b1 <
0:
0"
b0 9
b0 !
1)
11
1'
1/
b111111110100101 &
#1400
0)
01
#1405
b10 @
b10 <
06
b1 ;
b1111 7
b10000 8
1)
11
0'
0/
#1410
0)
01
#1415
b11 @
b11 <
16
1:
1"
b1 9
b1 !
1)
11
#1420
0)
01
#1425
1)
11
#1430
0)
01
#1435
b1 @
b1 <
0:
0"
b0 9
b0 !
1)
11
1'
1/
b1111111110101101 &
b1111111110101101 .
#1440
0)
01
#1445
b10 @
b10 <
06
b1 ;
b1111 7
b10000 8
1)
11
0'
0/
#1450
0)
01
#1455
b11 @
b11 <
16
1:
1"
b1 9
b1 !
1)
11
#1460
0)
01
#1465
1)
11
#1470
0)
01
#1475
b1 @
b1 <
0:
0"
b0 9
b0 !
1)
11
1'
1/
b1111111110101101 &
#1480
0)
01
#1485
b10 @
b10 <
06
b1 ;
b1111 7
b10000 8
1)
11
0'
0/
#1490
0)
01
#1495
b11 @
b11 <
16
1:
1"
b1 9
b1 !
1)
11
#1500
0)
01
#1505
1)
11
#1510
0)
01
#1515
b1 @
b1 <
0:
0"
b0 9
b0 !
1)
11
1'
1/
b1111111110101101 &
#1520
0)
01
#1525
b10 @
b10 <
06
b1 ;
b1111 7
b10000 8
1)
11
0'
0/
#1530
0)
01
#1535
b11 @
b11 <
16
1:
1"
b1 9
b1 !
1)
11
#1540
0)
01
#1545
1)
11
#1550
0)
01
#1555
b1 @
b1 <
0:
0"
b0 9
b0 !
1)
11
1'
1/
b1111111110101101 &
#1560
0)
01
#1565
b10 @
b10 <
06
b1 ;
b1111 7
b10000 8
1)
11
0'
0/
#1570
0)
01
#1575
b11 @
b11 <
16
1:
1"
b1 9
b1 !
1)
11
#1580
0)
01
#1585
1)
11
#1590
0)
01
#1595
b1 @
b1 <
0:
0"
b0 9
b0 !
1)
11
1'
1/
b1111111110101101 &
#1600
0)
01
#1605
b10 @
b10 <
06
b1 ;
b1111 7
b10000 8
1)
11
0'
0/
#1610
0)
01
#1615
b11 @
b11 <
16
1:
1"
b1 9
b1 !
1)
11
#1620
0)
01
#1625
1)
11
#1630
0)
01
#1635
b1 @
b1 <
0:
0"
b0 9
b0 !
1)
11
1'
1/
b1111111110101101 &
#1640
0)
01
#1645
b10 @
b10 <
06
b1 ;
b1111 7
b10000 8
1)
11
0'
0/
#1650
0)
01
#1655
b11 @
b11 <
16
1:
1"
b1 9
b1 !
1)
11
#1660
0)
01
#1665
1)
11
#1670
0)
01
#1675
b1 @
b1 <
0:
0"
b0 9
b0 !
1)
11
1'
1/
b1111111110101101 &
#1680
0)
01
#1685
b10 @
b10 <
06
b1 ;
b1111 7
b10000 8
1)
11
0'
0/
#1690
0)
01
#1695
b11 @
b11 <
16
1:
1"
b1 9
b1 !
1)
11
#1700
0)
01
#1705
1)
11
#1710
0)
01
#1715
b1 @
b1 <
0:
0"
b0 9
b0 !
1)
11
1'
1/
b1111111110101101 &
#1720
0)
01
#1725
b10 @
b10 <
06
b1 ;
b1111 7
b10000 8
1)
11
0'
0/
#1730
0)
01
#1735
b11 @
b11 <
16
1:
1"
b1 9
b1 !
1)
11
#1740
0)
01
#1745
1)
11
#1750
0)
01
#1755
b1 @
b1 <
0:
0"
b0 9
b0 !
1)
11
1'
1/
b1111111110101101 &
#1760
0)
01
#1765
b10 @
b10 <
06
b1 ;
b1111 7
b10000 8
1)
11
0'
0/
#1770
0)
01
#1775
b11 @
b11 <
16
1:
1"
b1 9
b1 !
1)
11
#1780
0)
01
#1785
1)
11
#1790
0)
01
#1795
b1 @
b1 <
0:
0"
b0 9
b0 !
1)
11
1'
1/
b1111111110101101 &
#1800
0)
01
#1805
b10 @
b10 <
06
b1 ;
b1111 7
b10000 8
1)
11
0'
0/
#1810
0)
01
#1815
b11 @
b11 <
16
1:
1"
b1 9
b1 !
1)
11
#1820
0)
01
#1825
1)
11
#1830
0)
01
#1835
b1 @
b1 <
0:
0"
b0 9
b0 !
1)
11
1'
1/
b1111111110101101 &
#1840
0)
01
#1845
b10 @
b10 <
06
b1 ;
b1111 7
b10000 8
1)
11
0'
0/
#1850
0)
01
#1855
b11 @
b11 <
16
1:
1"
b1 9
b1 !
1)
11
#1860
0)
01
#1865
1)
11
#1870
0)
01
#1875
b1 @
b1 <
0:
0"
b0 9
b0 !
1)
11
1'
1/
b1111111110101101 &
#1880
0)
01
#1885
b10 @
b10 <
06
b1 ;
b1111 7
b10000 8
1)
11
0'
0/
#1890
0)
01
#1895
b11 @
b11 <
16
1:
1"
b1 9
b1 !
1)
11
#1900
0)
01
#1905
1)
11
#1910
0)
01
#1915
b1 @
b1 <
0:
0"
b0 9
b0 !
1)
11
1'
1/
b1111111110101101 &
#1920
0)
01
#1925
b10 @
b10 <
06
b1 ;
b1111 7
b10000 8
1)
11
0'
0/
#1930
0)
01
#1935
b11 @
b11 <
16
1:
1"
b1 9
b1 !
1)
11
#1940
0)
01
#1945
1)
11
#1950
0)
01
#1955
b1 @
b1 <
0:
0"
b0 9
b0 !
1)
11
1'
1/
b1111111110101101 &
#1960
0)
01
#1965
b10 @
b10 <
06
b1 ;
b1111 7
b10000 8
1)
11
0'
0/
#1970
0)
01
#1975
b11 @
b11 <
16
1:
1"
b1 9
b1 !
1)
11
#1980
0)
01
#1985
1)
11
#1990
0)
01
#1995
b1 @
b1 <
0:
0"
b0 9
b0 !
1)
11
1'
1/
b1111111110101101 &
#2000
0)
01
#2005
b10 @
b10 <
06
b1 ;
b1111 7
b10000 8
1)
11
0'
0/
#2010
0)
01
#2015
b11 @
b11 <
16
1:
1"
b1 9
b1 !
1)
11
#2020
0)
01
#2025
1)
11
#2030
0)
01
#2035
b1 @
b1 <
0:
0"
b0 9
b0 !
1)
11
1'
1/
b1111111110101101 &
#2040
0)
01
#2045
b10 @
b10 <
06
b1 ;
b1111 7
b10000 8
1)
11
0'
0/
#2050
0)
01
#2055
b11 @
b11 <
16
1:
1"
b1 9
b1 !
1)
11
#2060
0)
01
#2065
1)
11
#2070
0)
01
#2075
b1 @
b1 <
0:
0"
b0 9
b0 !
1)
11
1'
1/
b1111111110101101 &
#2080
0)
01
#2085
b10 @
b10 <
06
b1 ;
b1111 7
b10000 8
1)
11
0'
0/
#2090
0)
01
#2095
b11 @
b11 <
16
1:
1"
b1 9
b1 !
1)
11
#2100
0)
01
#2105
1)
11
#2110
0)
01
#2115
b1 @
b1 <
0:
0"
b0 9
b0 !
1)
11
1'
1/
b1111111110101101 &
#2120
0)
01
#2125
b10 @
b10 <
06
b1 ;
b1111 7
b10000 8
1)
11
0'
0/
#2130
0)
01
#2135
b11 @
b11 <
16
1:
1"
b1 9
b1 !
1)
11
#2140
0)
01
#2145
1)
11
#2150
0)
01
#2155
b1 @
b1 <
0:
0"
b0 9
b0 !
1)
11
1'
1/
b1111111110101101 &
#2160
0)
01
#2165
b10 @
b10 <
06
b1 ;
b1111 7
b10000 8
1)
11
0'
0/
#2170
0)
01
#2175
b11 @
b11 <
16
1:
1"
b1 9
b1 !
1)
11
#2180
0)
01
#2185
1)
11
#2190
0)
01
#2195
b1 @
b1 <
0:
0"
b0 9
b0 !
1)
11
1'
1/
b1111111110101101 &
#2200
0)
01
#2205
b10 @
b10 <
06
b1 ;
b1111 7
b10000 8
1)
11
0'
0/
#2210
0)
01
#2215
b11 @
b11 <
16
1:
1"
b1 9
b1 !
1)
11
#2220
0)
01
#2225
1)
11
#2230
0)
01
#2235
b1 @
b1 <
0:
0"
b0 9
b0 !
1)
11
1'
1/
b1111111110101101 &
#2240
0)
01
#2245
b10 @
b10 <
06
b1 ;
b1111 7
b10000 8
1)
11
0'
0/
#2250
0)
01
#2255
b11 @
b11 <
16
1:
1"
b1 9
b1 !
1)
11
#2260
0)
01
#2265
1)
11
#2270
0)
01
#2275
b1 @
b1 <
0:
0"
b0 9
b0 !
1)
11
1'
1/
b1111111110101101 &
#2280
0)
01
#2285
b10 @
b10 <
06
b1 ;
b1111 7
b10000 8
1)
11
0'
0/
#2290
0)
01
#2295
b11 @
b11 <
16
1:
1"
b1 9
b1 !
1)
11
#2300
0)
01
#2305
1)
11
#2310
0)
01
#2315
b1 @
b1 <
0:
0"
b0 9
b0 !
1)
11
1'
1/
b1111111110101101 &
#2320
0)
01
#2325
b10 @
b10 <
06
b1 ;
b1111 7
b10000 8
1)
11
0'
0/
#2330
0)
01
#2335
b11 @
b11 <
16
1:
1"
b1 9
b1 !
1)
11
#2340
0)
01
#2345
1)
11
#2350
0)
01
#2355
b1 @
b1 <
0:
0"
b0 9
b0 !
1)
11
1'
1/
b1111111110101101 &
#2360
0)
01
#2365
b10 @
b10 <
06
b1 ;
b1111 7
b10000 8
1)
11
0'
0/
#2370
0)
01
#2375
b11 @
b11 <
16
1:
1"
b1 9
b1 !
1)
11
#2380
0)
01
#2385
1)
11
#2390
0)
01
#2395
b1 @
b1 <
0:
0"
b0 9
b0 !
1)
11
1'
1/
b1111111110101101 &
#2400
0)
01
#2405
b10 @
b10 <
06
b1 ;
b1111 7
b10000 8
1)
11
0'
0/
#2410
0)
01
#2415
b11 @
b11 <
16
1:
1"
b1 9
b1 !
1)
11
#2420
0)
01
#2425
1)
11
#2430
0)
01
#2435
b1 @
b1 <
0:
0"
b0 9
b0 !
1)
11
1'
1/
b1111111110101101 &
#2440
0)
01
#2445
b10 @
b10 <
06
b1 ;
b1111 7
b10000 8
1)
11
0'
0/
#2450
0)
01
#2455
b11 @
b11 <
16
1:
1"
b1 9
b1 !
1)
11
#2460
0)
01
