Watchdog Timer/design.sv
module watchdog_timer(
  //Processor
  pclk_i,prst_i,paddr_i,pwdata_i,prdata_o,pwrite_i,penable_i,pready_o,pslverr_o,
  //System Interface
  activity_i,sys_reset_o
);
  
  parameter S_RESET 			= 2'b00;
  parameter S_NO_ACTIVITY 		= 2'b01;
  parameter S_ACTIVITY 			= 2'b10;
  parameter S_THRESHOLD_TIMEOUT = 2'b11;
  
  input pclk_i,prst_i,pwrite_i,penable_i;
  input [7:0] paddr_i;
  input [7:0] pwdata_i;
  output reg [7:0] prdata_o;
  output reg pready_o;
  output reg pslverr_o;
  input activity_i;
  output reg sys_reset_o;
 
  integer no_activity_count;
  
  //Register to store the threshold value of the timer
  reg [7:0] threshold_timer_reg; //1 register
  
  //For State Machine to be implemented
  reg [2:0] state, next_state;
  
  always @(next_state) begin
    state = next_state;
  end
  
  //Process 1 - Programming the registers
  always @(posedge pclk_i) begin
    
    if(prst_i == 1) begin
      //Reset all the reg variables
      prdata_o = 0;
      pready_o = 0;
      pslverr_o = 0;
      state = S_RESET;
      next_state = S_RESET;
      sys_reset_o = 0;
      no_activity_count = 0;
    end
    
    else begin
      if (penable_i == 1) begin
        pready_o = 1;
        if(pwrite_i == 1) begin
          threshold_timer_reg = pwdata_i;
        end
        else begin
          prdata_o = threshold_timer_reg;
        end
      end
    end
  end
  
  //Process 2 - Implementing Watchdog Timer Functionality
  always @(posedge pclk_i) begin
    case(state)
  
      S_RESET: begin
        sys_reset_o = 0;
        if (activity_i == 1) begin
          next_state = S_ACTIVITY;
        end
        else begin
          next_state = S_NO_ACTIVITY;
          no_activity_count = no_activity_count + 1;
        end
      end
      
      S_NO_ACTIVITY: begin
        sys_reset_o = 0;
        if (activity_i == 0) begin
          no_activity_count = no_activity_count + 1;
          if(no_activity_count == threshold_timer_reg) begin
            next_state = S_THRESHOLD_TIMEOUT;
          end
        end
        else begin
          next_state = S_ACTIVITY;
        end
      end
      
      S_ACTIVITY: begin
        sys_reset_o = 0;
        no_activity_count = 0;
        if (activity_i == 1) begin
          next_state = S_ACTIVITY;
        end
        else begin
          next_state = S_NO_ACTIVITY;
        end
      end
      
      S_THRESHOLD_TIMEOUT: begin
        sys_reset_o = 1;
        next_state = S_NO_ACTIVITY;
        no_activity_count = 0;
      end
      
    endcase
  end
  
  
endmodule

Watchdog Timer/testbench.sv
module tb_watchdog_timer;
  
  reg pclk_i,prst_i,pwrite_i,penable_i;
  reg [7:0] paddr_i;
  reg [7:0] pwdata_i;
  reg activity_i;
  wire [7:0] prdata_o;
  wire pready_o;
  wire pslverr_o;
  wire sys_reset_o;
  
  watchdog_timer dut(
  //Processor
  pclk_i,prst_i,paddr_i,pwdata_i,prdata_o,pwrite_i,penable_i,pready_o,pslverr_o,
  //System Interface
  activity_i,sys_reset_o
);
  
  initial begin
    pclk_i = 0;
    forever #5 pclk_i = ~pclk_i;
  end
  
  initial begin
    prst_i = 1;
    activity_i = 0;
    paddr_i = 0;
    pwrite_i = 0;
    pwdata_i = 0;
    penable_i = 0;
    repeat(2) @(posedge pclk_i);
    prst_i = 0;
    
    //Program Register
    reg_write(0,200);
    #2000;
    activity_i = 1;
    #10;
    activity_i = 0;
    #1000;
    activity_i = 1;
    #3000;
    $finish;
  end
  
  task reg_write(input [7:0] addr, input [7:0] data);
    begin
      @(posedge pclk_i);
      paddr_i = addr;
      pwdata_i = data; //(i: giving Lowest Priority and 15-i: giving Highest Priority) (Can't use $random -> same priority might be assigned)
      pwrite_i = 1;
      penable_i = 1;
      wait (pready_o == 1);
      @(posedge pclk_i);
      pwrite_i = 0;
      penable_i = 0;
      paddr_i = 0;
      pwdata_i = 0;
    end
  endtask
  
  initial begin
    $dumpfile("intc.vcd");
    $dumpvars(0,tb_watchdog_timer);
  end
endmodule

Watchdog Timer/intc.vcd
$date
	Sun Jan 24 18:17:25 2021
$end
$version
	Icarus Verilog
$end
$timescale
	1s
$end
$scope module tb_watchdog_timer $end
$var wire 8 ! prdata_o [7:0] $end
$var wire 1 " pready_o $end
$var wire 1 # pslverr_o $end
$var wire 1 $ sys_reset_o $end
$var reg 1 % activity_i $end
$var reg 8 & paddr_i [7:0] $end
$var reg 1 ' pclk_i $end
$var reg 1 ( penable_i $end
$var reg 1 ) prst_i $end
$var reg 8 * pwdata_i [7:0] $end
$var reg 1 + pwrite_i $end
$scope module dut $end
$var wire 1 , activity_i $end
$var wire 8 - paddr_i [7:0] $end
$var wire 1 . pclk_i $end
$var wire 1 / penable_i $end
$var wire 1 0 prst_i $end
$var wire 8 1 pwdata_i [7:0] $end
$var wire 1 2 pwrite_i $end
$var reg 3 3 next_state [2:0] $end
$var integer 32 4 no_activity_count [31:0] $end
$var reg 8 5 prdata_o [7:0] $end
$var reg 1 6 pready_o $end
$var reg 1 7 pslverr_o $end
$var reg 3 8 state [2:0] $end
$var reg 1 9 sys_reset_o $end
$var reg 8 : threshold_timer_reg [7:0] $end
$upscope $end
$scope task reg_write $end
$var reg 8 ; addr [7:0] $end
$var reg 8 < data [7:0] $end
$upscope $end
$upscope $end
$enddefinitions $end
#0
$dumpvars
bx <
bx ;
bx :
x9
bx 8
x7
x6
bx 5
bx 4
bx 3
02
b0 1
10
0/
0.
b0 -
0,
0+
b0 *
1)
0(
0'
b0 &
0%
x$
x#
x"
bx !
$end
#5
b0 4
09
0$
b0 3
b0 8
07
0#
06
0"
b0 5
b0 !
1'
1.
#10
0'
0.
#15
b1 8
b11001000 <
b0 ;
0)
00
b1 4
b1 3
1'
1.
#20
0'
0.
#25
b11001000 :
16
1"
b10 4
1(
1/
1+
12
b11001000 *
b11001000 1
1'
1.
#30
0'
0.
#35
b11 4
b0 *
b0 1
0(
0/
0+
02
1'
1.
#40
0'
0.
#45
b100 4
1'
1.
#50
0'
0.
#55
b101 4
1'
1.
#60
0'
0.
#65
b110 4
1'
1.
#70
0'
0.
#75
b111 4
1'
1.
#80
0'
0.
#85
b1000 4
1'
1.
#90
0'
0.
#95
b1001 4
1'
1.
#100
0'
0.
#105
b1010 4
1'
1.
#110
0'
0.
#115
b1011 4
1'
1.
#120
0'
0.
#125
b1100 4
1'
1.
#130
0'
0.
#135
b1101 4
1'
1.
#140
0'
0.
#145
b1110 4
1'
1.
#150
0'
0.
#155
b1111 4
1'
1.
#160
0'
0.
#165
b10000 4
1'
1.
#170
0'
0.
#175
b10001 4
1'
1.
#180
0'
0.
#185
b10010 4
1'
1.
#190
0'
0.
#195
b10011 4
1'
1.
#200
0'
0.
#205
b10100 4
1'
1.
#210
0'
0.
#215
b10101 4
1'
1.
#220
0'
0.
#225
b10110 4
1'
1.
#230
0'
0.
#235
b10111 4
1'
1.
#240
0'
0.
#245
b11000 4
1'
1.
#250
0'
0.
#255
b11001 4
1'
1.
#260
0'
0.
#265
b11010 4
1'
1.
#270
0'
0.
#275
b11011 4
1'
1.
#280
0'
0.
#285
b11100 4
1'
1.
#290
0'
0.
#295
b11101 4
1'
1.
#300
0'
0.
#305
b11110 4
1'
1.
#310
0'
0.
#315
b11111 4
1'
1.
#320
0'
0.
#325
b100000 4
1'
1.
#330
0'
0.
#335
b100001 4
1'
1.
#340
0'
0.
#345
b100010 4
1'
1.
#350
0'
0.
#355
b100011 4
1'
1.
#360
0'
0.
#365
b100100 4
1'
1.
#370
0'
0.
#375
b100101 4
1'
1.
#380
0'
0.
#385
b100110 4
1'
1.
#390
0'
0.
#395
b100111 4
1'
1.
#400
0'
0.
#405
b101000 4
1'
1.
#410
0'
0.
#415
b101001 4
1'
1.
#420
0'
0.
#425
b101010 4
1'
1.
#430
0'
0.
#435
b101011 4
1'
1.
#440
0'
0.
#445
b101100 4
1'
1.
#450
0'
0.
#455
b101101 4
1'
1.
#460
0'
0.
#465
b101110 4
1'
1.
#470
0'
0.
#475
b101111 4
1'
1.
#480
0'
0.
#485
b110000 4
1'
1.
#490
0'
0.
#495
b110001 4
1'
1.
#500
0'
0.
#505
b110010 4
1'
1.
#510
0'
0.
#515
b110011 4
1'
1.
#520
0'
0.
#525
b110100 4
1'
1.
#530
0'
0.
#535
b110101 4
1'
1.
#540
0'
0.
#545
b110110 4
1'
1.
#550
0'
0.
#555
b110111 4
1'
1.
#560
0'
0.
#565
b111000 4
1'
1.
#570
0'
0.
#575
b111001 4
1'
1.
#580
0'
0.
#585
b111010 4
1'
1.
#590
0'
0.
#595
b111011 4
1'
1.
#600
0'
0.
#605
b111100 4
1'
1.
#610
0'
0.
#615
b111101 4
1'
1.
#620
0'
0.
#625
b111110 4
1'
1.
#630
0'
0.
#635
b111111 4
1'
1.
#640
0'
0.
#645
b1000000 4
1'
1.
#650
0'
0.
#655
b1000001 4
1'
1.
#660
0'
0.
#665
b1000010 4
1'
1.
#670
0'
0.
#675
b1000011 4
1'
1.
#680
0'
0.
#685
b1000100 4
1'
1.
#690
0'
0.
#695
b1000101 4
1'
1.
#700
0'
0.
#705
b1000110 4
1'
1.
#710
0'
0.
#715
b1000111 4
1'
1.
#720
0'
0.
#725
b1001000 4
1'
1.
#730
0'
0.
#735
b1001001 4
1'
1.
#740
0'
0.
#745
b1001010 4
1'
1.
#750
0'
0.
#755
b1001011 4
1'
1.
#760
0'
0.
#765
b1001100 4
1'
1.
#770
0'
0.
#775
b1001101 4
1'
1.
#780
0'
0.
#785
b1001110 4
1'
1.
#790
0'
0.
#795
b1001111 4
1'
1.
#800
0'
0.
#805
b1010000 4
1'
1.
#810
0'
0.
#815
b1010001 4
1'
1.
#820
0'
0.
#825
b1010010 4
1'
1.
#830
0'
0.
#835
b1010011 4
1'
1.
#840
0'
0.
#845
b1010100 4
1'
1.
#850
0'
0.
#855
b1010101 4
1'
1.
#860
0'
0.
#865
b1010110 4
1'
1.
#870
0'
0.
#875
b1010111 4
1'
1.
#880
0'
0.
#885
b1011000 4
1'
1.
#890
0'
0.
#895
b1011001 4
1'
1.
#900
0'
0.
#905
b1011010 4
1'
1.
#910
0'
0.
#915
b1011011 4
1'
1.
#920
0'
0.
#925
b1011100 4
1'
1.
#930
0'
0.
#935
b1011101 4
1'
1.
#940
0'
0.
#945
b1011110 4
1'
1.
#950
0'
0.
#955
b1011111 4
1'
1.
#960
0'
0.
#965
b1100000 4
1'
1.
#970
0'
0.
#975
b1100001 4
1'
1.
#980
0'
0.
#985
b1100010 4
1'
1.
#990
0'
0.
#995
b1100011 4
1'
1.
#1000
0'
0.
#1005
b1100100 4
1'
1.
#1010
0'
0.
#1015
b1100101 4
1'
1.
#1020
0'
0.
#1025
b1100110 4
1'
1.
#1030
0'
0.
#1035
b1100111 4
1'
1.
#1040
0'
0.
#1045
b1101000 4
1'
1.
#1050
0'
0.
#1055
b1101001 4
1'
1.
#1060
0'
0.
#1065
b1101010 4
1'
1.
#1070
0'
0.
#1075
b1101011 4
1'
1.
#1080
0'
0.
#1085
b1101100 4
1'
1.
#1090
0'
0.
#1095
b1101101 4
1'
1.
#1100
0'
0.
#1105
b1101110 4
1'
1.
#1110
0'
0.
#1115
b1101111 4
1'
1.
#1120
0'
0.
#1125
b1110000 4
1'
1.
#1130
0'
0.
#1135
b1110001 4
1'
1.
#1140
0'
0.
#1145
b1110010 4
1'
1.
#1150
0'
0.
#1155
b1110011 4
1'
1.
#1160
0'
0.
#1165
b1110100 4
1'
1.
#1170
0'
0.
#1175
b1110101 4
1'
1.
#1180
0'
0.
#1185
b1110110 4
1'
1.
#1190
0'
0.
#1195
b1110111 4
1'
1.
#1200
0'
0.
#1205
b1111000 4
1'
1.
#1210
0'
0.
#1215
b1111001 4
1'
1.
#1220
0'
0.
#1225
b1111010 4
1'
1.
#1230
0'
0.
#1235
b1111011 4
1'
1.
#1240
0'
0.
#1245
b1111100 4
1'
1.
#1250
0'
0.
#1255
b1111101 4
1'
1.
#1260
0'
0.
#1265
b1111110 4
1'
1.
#1270
0'
0.
#1275
b1111111 4
1'
1.
#1280
0'
0.
#1285
b10000000 4
1'
1.
#1290
0'
0.
#1295
b10000001 4
1'
1.
#1300
0'
0.
#1305
b10000010 4
1'
1.
#1310
0'
0.
#1315
b10000011 4
1'
1.
#1320
0'
0.
#1325
b10000100 4
1'
1.
#1330
0'
0.
#1335
b10000101 4
1'
1.
#1340
0'
0.
#1345
b10000110 4
1'
1.
#1350
0'
0.
#1355
b10000111 4
1'
1.
#1360
0'
0.
#1365
b10001000 4
1'
1.
#1370
0'
0.
#1375
b10001001 4
1'
1.
#1380
0'
0.
#1385
b10001010 4
1'
1.
#1390
0'
0.
#1395
b10001011 4
1'
1.
#1400
0'
0.
#1405
b10001100 4
1'
1.
#1410
0'
0.
#1415
b10001101 4
1'
1.
#1420
0'
0.
#1425
b10001110 4
1'
1.
#1430
0'
0.
#1435
b10001111 4
1'
1.
#1440
0'
0.
#1445
b10010000 4
1'
1.
#1450
0'
0.
#1455
b10010001 4
1'
1.
#1460
0'
0.
#1465
b10010010 4
1'
1.
#1470
0'
0.
#1475
b10010011 4
1'
1.
#1480
0'
0.
#1485
b10010100 4
1'
1.
#1490
0'
0.
#1495
b10010101 4
1'
1.
#1500
0'
0.
#1505
b10010110 4
1'
1.
#1510
0'
0.
#1515
b10010111 4
1'
1.
#1520
0'
0.
#1525
b10011000 4
1'
1.
#1530
0'
0.
#1535
b10011001 4
1'
1.
#1540
0'
0.
#1545
b10011010 4
1'
1.
#1550
0'
0.
#1555
b10011011 4
1'
1.
#1560
0'
0.
#1565
b10011100 4
1'
1.
#1570
0'
0.
#1575
b10011101 4
1'
1.
#1580
0'
0.
#1585
b10011110 4
1'
1.
#1590
0'
0.
#1595
b10011111 4
1'
1.
#1600
0'
0.
#1605
b10100000 4
1'
1.
#1610
0'
0.
#1615
b10100001 4
1'
1.
#1620
0'
0.
#1625
b10100010 4
1'
1.
#1630
0'
0.
#1635
b10100011 4
1'
1.
#1640
0'
0.
#1645
b10100100 4
1'
1.
#1650
0'
0.
#1655
b10100101 4
1'
1.
#1660
0'
0.
#1665
b10100110 4
1'
1.
#1670
0'
0.
#1675
b10100111 4
1'
1.
#1680
0'
0.
#1685
b10101000 4
1'
1.
#1690
0'
0.
#1695
b10101001 4
1'
1.
#1700
0'
0.
#1705
b10101010 4
1'
1.
#1710
0'
0.
#1715
b10101011 4
1'
1.
#1720
0'
0.
#1725
b10101100 4
1'
1.
#1730
0'
0.
#1735
b10101101 4
1'
1.
#1740
0'
0.
#1745
b10101110 4
1'
1.
#1750
0'
0.
#1755
b10101111 4
1'
1.
#1760
0'
0.
#1765
b10110000 4
1'
1.
#1770
0'
0.
#1775
b10110001 4
1'
1.
#1780
0'
0.
#1785
b10110010 4
1'
1.
#1790
0'
0.
#1795
b10110011 4
1'
1.
#1800
0'
0.
#1805
b10110100 4
1'
1.
#1810
0'
0.
#1815
b10110101 4
1'
1.
#1820
0'
0.
#1825
b10110110 4
1'
1.
#1830
0'
0.
#1835
b10110111 4
1'
1.
#1840
0'
0.
#1845
b10111000 4
1'
1.
#1850
0'
0.
#1855
b10111001 4
1'
1.
#1860
0'
0.
#1865
b10111010 4
1'
1.
#1870
0'
0.
#1875
b10111011 4
1'
1.
#1880
0'
0.
#1885
b10111100 4
1'
1.
#1890
0'
0.
#1895
b10111101 4
1'
1.
#1900
0'
0.
#1905
b10111110 4
1'
1.
#1910
0'
0.
#1915
b10111111 4
1'
1.
#1920
0'
0.
#1925
b11000000 4
1'
1.
#1930
0'
0.
#1935
b11000001 4
1'
1.
#1940
0'
0.
#1945
b11000010 4
1'
1.
#1950
0'
0.
#1955
b11000011 4
1'
1.
#1960
0'
0.
#1965
b11000100 4
1'
1.
#1970
0'
0.
#1975
b11000101 4
1'
1.
#1980
0'
0.
#1985
b11000110 4
1'
1.
#1990
0'
0.
#1995
b11000111 4
1'
1.
#2000
0'
0.
#2005
b11 8
b11 3
b11001000 4
1'
1.
#2010
0'
0.
#2015
b1 8
b0 4
b1 3
19
1$
1'
1.
#2020
0'
0.
#2025
b1 4
09
0$
1'
1.
#2030
0'
0.
#2035
b10 8
b10 3
1'
1.
1%
1,
#2040
0'
0.
#2045
b1 8
b1 3
b0 4
1'
1.
0%
0,
#2050
0'
0.
#2055
b1 4
1'
1.
#2060
0'
0.
#2065
b10 4
1'
1.
#2070
0'
0.
#2075
b11 4
1'
1.
#2080
0'
0.
#2085
b100 4
1'
1.
#2090
0'
0.
#2095
b101 4
1'
1.
#2100
0'
0.
#2105
b110 4
1'
1.
#2110
0'
0.
#2115
b111 4
1'
1.
#2120
0'
0.
#2125
b1000 4
1'
1.
#2130
0'
0.
#2135
b1001 4
1'
1.
#2140
0'
0.
#2145
b1010 4
1'
1.
#2150
0'
0.
#2155
b1011 4
1'
1.
#2160
0'
0.
#2165
b1100 4
1'
1.
#2170
0'
0.
#2175
b1101 4
1'
1.
#2180
0'
0.
#2185
b1110 4
1'
1.
#2190
0'
0.
#2195
b1111 4
1'
1.
#2200
0'
0.
#2205
b10000 4
1'
1.
#2210
0'
0.
#2215
b10001 4
1'
1.
#2220
0'
0.
#2225
b10010 4
1'
1.
#2230
0'
0.
#2235
b10011 4
1'
1.
#2240
0'
0.
#2245
b10100 4
1'
1.
#2250
0'
0.
#2255
b10101 4
1'
1.
#2260
0'
0.
#2265
b10110 4
1'
1.
#2270
0'
0.
#2275
b10111 4
1'
1.
#2280
0'
0.
#2285
b11000 4
1'
1.
#2290
0'
0.
#2295
b11001 4
1'
1.
#2300
0'
0.
#2305
b11010 4
1'
1.
#2310
0'
0.
#2315
b11011 4
1'
1.
#2320
0'
0.
#2325
b11100 4
1'
1.
#2330
0'
0.
#2335
b11101 4
1'
1.
#2340
0'
0.
#2345
b11110 4
1'
1.
#2350
0'
0.
#2355
b11111 4
1'
1.
#2360
0'
0.
#2365
b100000 4
1'
1.
#2370
0'
0.
#2375
b100001 4
1'
1.
#2380
0'
0.
#2385
b100010 4
1'
1.
#2390
0'
0.
#2395
b100011 4
1'
1.
#2400
0'
0.
#2405
b100100 4
1'
1.
#2410
0'
0.
#2415
b100101 4
1'
1.
#2420
0'
0.
#2425
b100110 4
1'
1.
#2430
0'
0.
#2435
b100111 4
1'
1.
#2440
0'
0.
#2445
b101000 4
1'
1.
#2450
0'
0.
#2455
b101001 4
1'
1.
#2460
0'
0.
#2465
b101010 4
1'
1.
#2470
0'
0.
#2475
b101011 4
1'
1.
#2480
0'
0.
#2485
b101100 4
1'
1.
#2490
0'
0.
#2495
b101101 4
1'
1.
#2500
0'
0.
#2505
b101110 4
1'
1.
#2510
0'
0.
#2515
b101111 4
1'
1.
#2520
0'
0.
#2525
b110000 4
1'
1.
#2530
0'
0.
#2535
b110001 4
1'
1.
#2540
0'
0.
#2545
b110010 4
1'
1.
#2550
0'
0.
#2555
b110011 4
1'
1.
#2560
0'
0.
#2565
b110100 4
1'
1.
#2570
0'
0.
#2575
b110101 4
1'
1.
#2580
0'
0.
#2585
b110110 4
1'
1.
#2590
0'
0.
#2595
b110111 4
1'
1.
#2600
0'
0.
#2605
b111000 4
1'
1.
#2610
0'
0.
#2615
b111001 4
1'
1.
#2620
0'
0.
#2625
b111010 4
1'
1.
#2630
0'
0.
#2635
b111011 4
1'
1.
#2640
0'
0.
#2645
b111100 4
1'
1.
#2650
0'
0.
#2655
b111101 4
1'
1.
#2660
0'
0.
#2665
b111110 4
1'
1.
#2670
0'
0.
#2675
b111111 4
1'
1.
#2680
0'
0.
#2685
b1000000 4
1'
1.
#2690
0'
0.
#2695
b1000001 4
1'
1.
#2700
0'
0.
#2705
b1000010 4
1'
1.
#2710
0'
0.
#2715
b1000011 4
1'
1.
#2720
0'
0.
#2725
b1000100 4
1'
1.
#2730
0'
0.
#2735
b1000101 4
1'
1.
#2740
0'
0.
#2745
b1000110 4
1'
1.
#2750
0'
0.
#2755
b1000111 4
1'
1.
#2760
0'
0.
#2765
b1001000 4
1'
1.
#2770
0'
0.
#2775
b1001001 4
1'
1.
#2780
0'
0.
#2785
b1001010 4
1'
1.
#2790
0'
0.
#2795
b1001011 4
1'
1.
#2800
0'
0.
#2805
b1001100 4
1'
1.
#2810
0'
0.
#2815
b1001101 4
1'
1.
#2820
0'
0.
#2825
b1001110 4
1'
1.
#2830
0'
0.
#2835
b1001111 4
1'
1.
#2840
0'
0.
#2845
b1010000 4
1'
1.
#2850
0'
0.
#2855
b1010001 4
1'
1.
#2860
0'
0.
#2865
b1010010 4
1'
1.
#2870
0'
0.
#2875
b1010011 4
1'
1.
#2880
0'
0.
#2885
b1010100 4
1'
1.
#2890
0'
0.
#2895
b1010101 4
1'
1.
#2900
0'
0.
#2905
b1010110 4
1'
1.
#2910
0'
0.
#2915
b1010111 4
1'
1.
#2920
0'
0.
#2925
b1011000 4
1'
1.
#2930
0'
0.
#2935
b1011001 4
1'
1.
#2940
0'
0.
#2945
b1011010 4
1'
1.
#2950
0'
0.
#2955
b1011011 4
1'
1.
#2960
0'
0.
#2965
b1011100 4
1'
1.
#2970
0'
0.
#2975
b1011101 4
1'
1.
#2980
0'
0.
#2985
b1011110 4
1'
1.
#2990
0'
0.
#2995
b1011111 4
1'
1.
#3000
0'
0.
#3005
b1100000 4
1'
1.
#3010
0'
0.
#3015
b1100001 4
1'
1.
#3020
0'
0.
#3025
b1100010 4
1'
1.
#3030
0'
0.
#3035
b1100011 4
1'
1.
#3040
0'
0.
#3045
b10 8
b10 3
1'
1.
1%
1,
#3050
0'
0.
#3055
b0 4
1'
1.
